ChineseTimeNLPMod/__init__.py
ChineseTimeNLPMod/enums.py
ChineseTimeNLPMod/normalizer.py
ChineseTimeNLPMod/point.py
ChineseTimeNLPMod/result.py
ChineseTimeNLPMod/unit.py
ChineseTimeNLPMod/helpers/LunarSolarConverter.py
ChineseTimeNLPMod/helpers/__init__.py
ChineseTimeNLPMod/helpers/arrow_helper.py
ChineseTimeNLPMod/helpers/int_common.py
ChineseTimeNLPMod/helpers/str_common.py
ChineseTimeNLPMod/resource/__init__.py
ChineseTimeNLPMod/resource/holiday.py
ChineseTimeNLPMod/resource/pattern.py
ChineseTimeNLPMod/tests/__init__.py
ChineseTimeNLPMod/tests/conftest.py
ChineseTimeNLPMod/tests/test_normalizer.py
ChineseTimeNLPMod/tests/test_point.py
ChineseTimeNLPMod/tests/test_utils.py
ChineseTimeNLPMod-1.3.0.dist-info/LICENSE
ChineseTimeNLPMod-1.3.0.dist-info/METADATA
ChineseTimeNLPMod-1.3.0.dist-info/WHEEL
ChineseTimeNLPMod-1.3.0.dist-info/top_level.txt
ChineseTimeNLPMod-1.3.0.dist-info/RECORD
