Metadata-Version: 2.1
Name: ChineseTimeNLPMod
Version: 1.3.0
Summary: 将中文时间表达词转为相应的时间字符串，支持时间点，时间段，时间间隔。
Home-page: https://github.com/iamtes1a/ChineseTimeNLP
Author: liveid
Author-email: 
License: MIT Licence
Keywords: chinese time,chinese time nlp
Platform: UNKNOWN
Classifier: Programming Language :: Python :: 3.8
License-File: LICENSE
Requires-Dist: arrow (>=0.17.0)
Requires-Dist: loguru (>=0.5.3)
Requires-Dist: regex (>=2020.11.13)
